python_smail-0.9.0.dist-info/DESCRIPTION.rst
python_smail-0.9.0.dist-info/METADATA
python_smail-0.9.0.dist-info/RECORD
python_smail-0.9.0.dist-info/WHEEL
python_smail-0.9.0.dist-info/metadata.json
python_smail-0.9.0.dist-info/top_level.txt
smail/__init__.py
smail/ciphers.py
smail/encrypt.py
smail/message.py
smail/sign.py
smail/sign_encrypt.py
smail/signer.py
smail/utils.py
smail/version.py
