Metadata-Version: 2.0
Name: python-smail
Version: 0.9.0
Summary: Simple S/MIME e-mails with Python3
Home-page: https://gitlab.com/rhab/python-smail
Author: Robert Habermann
Author-email: mail@rhab.de
License: Apache License (2.0)
Keywords: smime cryptography email S/MIME encrypt sign
Platform: all
Classifier: Development Status :: 4 - Beta
Classifier: Operating System :: OS Independent
Classifier: Intended Audience :: Developers
Classifier: License :: OSI Approved :: Apache Software License
Classifier: Programming Language :: Python :: 3
Classifier: Programming Language :: Python :: 3.5
Classifier: Programming Language :: Python :: 3.6
Classifier: Programming Language :: Python :: 3.7
Classifier: Programming Language :: Python :: 3.8
Classifier: Topic :: Software Development :: Libraries
Classifier: Topic :: Communications :: Email
Classifier: Topic :: Security :: Cryptography
Requires-Dist: asn1crypto
Requires-Dist: oscrypto
Provides-Extra: test
Requires-Dist: coverage; extra == 'test'
Requires-Dist: flake8; extra == 'test'
Requires-Dist: tox; extra == 'test'
